crtsearch/__init__.py
crtsearch/crtsearch.py
crtsearch-1.0.1.dist-info/LICENSE
crtsearch-1.0.1.dist-info/METADATA
crtsearch-1.0.1.dist-info/WHEEL
crtsearch-1.0.1.dist-info/entry_points.txt
crtsearch-1.0.1.dist-info/top_level.txt
crtsearch-1.0.1.dist-info/RECORD
