Metadata-Version: 2.1
Name: crtsearch
Version: 1.0.1
Summary: A Tool written in Python3 for scraping data from crt.sh
Home-page: https://github.com/thehackersbrain/crtsearch
Author: Gaurav Raj
Author-email: techw803@gmail.com
License: MIT
Keywords: crt.sh,subdomains,thehackersbrain,gauravraj,python3
Platform: UNKNOWN
License-File: LICENSE
Requires-Dist: requests
Requires-Dist: rich
